Metadata-Version: 2.4
Name: coqui-tts
Version: 0.27.4
Summary: Deep learning for Text to Speech.
Project-URL: Homepage, https://github.com/idiap/coqui-ai-TTS
Project-URL: Documentation, https://coqui-tts.readthedocs.io
Project-URL: Repository, https://github.com/idiap/coqui-ai-TTS
Project-URL: Issues, https://github.com/idiap/coqui-ai-TTS/issues
Project-URL: Discussions, https://github.com/idiap/coqui-ai-TTS/discussions
Author-email: Eren Gölge <egolge@coqui.ai>
Maintainer-email: Enno Hermann <enno.hermann@gmail.com>
License: MPL-2.0
License-File: LICENSE.txt
Classifier: Development Status :: 4 - Beta
Classifier: Intended Audience :: Developers
Classifier: Intended Audience :: Science/Research
Classifier: License :: OSI Approved :: Mozilla Public License 2.0 (MPL 2.0)
Classifier: Operating System :: POSIX :: Linux
Classifier: Programming Language :: Python
Classifier: Programming Language :: Python :: 3
Classifier: Programming Language :: Python :: 3.10
Classifier: Programming Language :: Python :: 3.11
Classifier: Programming Language :: Python :: 3.12
Classifier: Programming Language :: Python :: 3.13
Classifier: Programming Language :: Python :: 3.14
Classifier: Topic :: Multimedia
Classifier: Topic :: Multimedia :: Sound/Audio
Classifier: Topic :: Multimedia :: Sound/Audio :: Speech
Classifier: Topic :: Scientific/Engineering :: Artificial Intelligence
Classifier: Topic :: Software Development
Classifier: Topic :: Software Development :: Libraries :: Python Modules
Requires-Python: <3.15,>=3.10
Requires-Dist: anyascii>=0.3.0
Requires-Dist: coqpit-config<0.3.0,>=0.2.0
Requires-Dist: coqui-tts-trainer<0.4.0,>=0.3.0
Requires-Dist: einops>=0.6.0
Requires-Dist: fsspec[http]>=2023.6.0
Requires-Dist: inflect>=5.6.0
Requires-Dist: ko-speech-tools>=0.1.0
Requires-Dist: librosa>=0.11.0
Requires-Dist: matplotlib>=3.8.4
Requires-Dist: monotonic-alignment-search>=0.1.0
Requires-Dist: num2words>=0.5.14
Requires-Dist: numba>=0.58.0
Requires-Dist: numpy>=1.26.0
Requires-Dist: packaging>=23.1
Requires-Dist: pysbd>=0.3.4
Requires-Dist: pyyaml>=6.0
Requires-Dist: scipy>=1.13.0
Requires-Dist: soundfile>=0.12.0
Requires-Dist: tqdm>=4.64.1
Requires-Dist: transformers>=4.57
Requires-Dist: typing-extensions>=4.10
Provides-Extra: all
Requires-Dist: bangla>=0.0.2; extra == 'all'
Requires-Dist: bnnumerizer>=0.0.2; extra == 'all'
Requires-Dist: bnunicodenormalizer>=0.1.0; extra == 'all'
Requires-Dist: bokeh>=3.0.3; extra == 'all'
Requires-Dist: cutlet>=0.2.0; extra == 'all'
Requires-Dist: flask>=3.0.0; extra == 'all'
Requires-Dist: fugashi[unidic-lite]>=1.3.0; extra == 'all'
Requires-Dist: gruut[de,es,fr]>=2.4.0; extra == 'all'
Requires-Dist: ko-speech-tools[g2p]>=0.1.0; (python_version < '3.14') and extra == 'all'
Requires-Dist: pandas<3.0,>=1.4; extra == 'all'
Requires-Dist: pypinyin>=0.40.0; extra == 'all'
Requires-Dist: spacy-pkuseg>=1.0.1; extra == 'all'
Requires-Dist: tqdm[notebook]>=4.64.1; extra == 'all'
Requires-Dist: umap-learn>=0.5.1; extra == 'all'
Requires-Dist: uroman>=1.3.1.1; extra == 'all'
Provides-Extra: bn
Requires-Dist: bangla>=0.0.2; extra == 'bn'
Requires-Dist: bnnumerizer>=0.0.2; extra == 'bn'
Requires-Dist: bnunicodenormalizer>=0.1.0; extra == 'bn'
Provides-Extra: codec
Requires-Dist: torchcodec>=0.8.0; extra == 'codec'
Provides-Extra: codec-cuda
Requires-Dist: torchcodec>=0.8.0; extra == 'codec-cuda'
Provides-Extra: cpu
Requires-Dist: torch>=2.2; extra == 'cpu'
Requires-Dist: torchaudio>=2.2.0; extra == 'cpu'
Provides-Extra: cuda
Requires-Dist: torch>=2.2; extra == 'cuda'
Requires-Dist: torchaudio>=2.2.0; extra == 'cuda'
Provides-Extra: ja
Requires-Dist: cutlet>=0.2.0; extra == 'ja'
Requires-Dist: fugashi[unidic-lite]>=1.3.0; extra == 'ja'
Provides-Extra: ko
Requires-Dist: ko-speech-tools[g2p]>=0.1.0; (python_version < '3.14') and extra == 'ko'
Provides-Extra: languages
Requires-Dist: bangla>=0.0.2; extra == 'languages'
Requires-Dist: bnnumerizer>=0.0.2; extra == 'languages'
Requires-Dist: bnunicodenormalizer>=0.1.0; extra == 'languages'
Requires-Dist: cutlet>=0.2.0; extra == 'languages'
Requires-Dist: fugashi[unidic-lite]>=1.3.0; extra == 'languages'
Requires-Dist: gruut[de,es,fr]>=2.4.0; extra == 'languages'
Requires-Dist: ko-speech-tools[g2p]>=0.1.0; (python_version < '3.14') and extra == 'languages'
Requires-Dist: pypinyin>=0.40.0; extra == 'languages'
Requires-Dist: spacy-pkuseg>=1.0.1; extra == 'languages'
Requires-Dist: uroman>=1.3.1.1; extra == 'languages'
Provides-Extra: notebooks
Requires-Dist: bokeh>=3.0.3; extra == 'notebooks'
Requires-Dist: pandas<3.0,>=1.4; extra == 'notebooks'
Requires-Dist: tqdm[notebook]>=4.64.1; extra == 'notebooks'
Requires-Dist: umap-learn>=0.5.1; extra == 'notebooks'
Provides-Extra: server
Requires-Dist: flask>=3.0.0; extra == 'server'
Provides-Extra: zh
Requires-Dist: pypinyin>=0.40.0; extra == 'zh'
Requires-Dist: spacy-pkuseg>=1.0.1; extra == 'zh'
